mytecz_omnitoken-0.1.5.dist-info/licenses/LICENSE
omnitoken/__init__.py
omnitoken/cli.py
omnitoken/tokenizer_base.py
omnitoken/tokenizer_bpe.py
omnitoken/tokenizer_hybrid.py
omnitoken/tokenizer_sentencepiece.py
omnitoken/tokenizer_wordpiece.py
omnitoken/trainer.py
omnitoken/utils.py
omnitoken/data/test_samples/roundtrip_expected.json
omnitoken/data/test_samples/small_texts.txt
omnitoken/data/test_samples/unicode_cases.txt
omnitoken/data/training_corpus/code_snippets.txt
omnitoken/data/training_corpus/emojis.txt
omnitoken/data/training_corpus/english.txt
omnitoken/data/training_corpus/json_samples.json
omnitoken/data/training_corpus/multilingual.txt
mytecz_omnitoken-0.1.5.dist-info/METADATA
mytecz_omnitoken-0.1.5.dist-info/WHEEL
mytecz_omnitoken-0.1.5.dist-info/entry_points.txt
mytecz_omnitoken-0.1.5.dist-info/top_level.txt
mytecz_omnitoken-0.1.5.dist-info/RECORD
