Metadata-Version: 2.4
Name: mytecz-omnitoken
Version: 0.1.5
Summary: Universal tokenizer with modular architecture supporting multiple tokenization strategies
Author-email: Kalyana Krishna Kondapalli <kalyanakondapalli@gmail.com>
Maintainer-email: Kalyana Krishna Kondapalli <kalyanakondapalli@gmail.com>
License: MIT License
Project-URL: Homepage, https://github.com/kalyanakkondapalli/mytecz_omnitoken
Project-URL: Documentation, https://github.com/kalyanakkondapalli/mytecz_omnitoken#readme
Project-URL: Repository, https://github.com/kalyanakkondapalli/mytecz_omnitoken.git
Project-URL: Bug Tracker, https://github.com/kalyanakkondapalli/mytecz_omnitoken/issues
Project-URL: Source Code, https://github.com/kalyanakkondapalli/mytecz_omnitoken
Keywords: tokenizer,nlp,natural-language-processing,bpe,wordpiece,sentencepiece,subword,machine-learning,text-processing,unicode,multilingual,hybrid-tokenization
Classifier: Development Status :: 4 - Beta
Classifier: Intended Audience :: Developers
Classifier: Intended Audience :: Science/Research
Classifier: Operating System :: OS Independent
Classifier: Programming Language :: Python :: 3
Classifier: Programming Language :: Python :: 3.10
Classifier: Programming Language :: Python :: 3.11
Classifier: Programming Language :: Python :: 3.12
Classifier: Programming Language :: Python :: 3.13
Classifier: License :: OSI Approved :: MIT License
Classifier: Topic :: Scientific/Engineering :: Artificial Intelligence
Classifier: Topic :: Software Development :: Libraries :: Python Modules
Classifier: Topic :: Text Processing :: Linguistic
Classifier: Typing :: Typed
Requires-Python: >=3.10
License-File: LICENSE
Provides-Extra: dev
Requires-Dist: pytest>=7.0; extra == "dev"
Requires-Dist: pytest-cov>=4.0; extra == "dev"
Requires-Dist: black>=23.0; extra == "dev"
Requires-Dist: ruff>=0.1.0; extra == "dev"
Requires-Dist: mypy>=1.0; extra == "dev"
Requires-Dist: pre-commit>=3.0; extra == "dev"
Provides-Extra: test
Requires-Dist: pytest>=7.0; extra == "test"
Requires-Dist: pytest-cov>=4.0; extra == "test"
Requires-Dist: pytest-xdist>=3.0; extra == "test"
Provides-Extra: examples
Requires-Dist: jupyter>=1.0; extra == "examples"
Requires-Dist: matplotlib>=3.5; extra == "examples"
Requires-Dist: pandas>=1.5; extra == "examples"
Requires-Dist: rich>=13.0; extra == "examples"
Provides-Extra: performance
Requires-Dist: numpy>=1.24; extra == "performance"
Requires-Dist: cython>=3.0; extra == "performance"
Provides-Extra: all
Requires-Dist: mytecz-omnitoken[dev,examples,performance,test]; extra == "all"
Dynamic: license-file
